insilicova-0.1.3.dist-info/RECORD
insilicova-0.1.3.dist-info/LICENSE
insilicova-0.1.3.dist-info/WHEEL
insilicova-0.1.3.dist-info/top_level.txt
insilicova-0.1.3.dist-info/METADATA
insilicova/__init__.py
insilicova/api.py
insilicova/indiv.py
insilicova/utils.py
insilicova/diag.py
insilicova/exceptions.py
insilicova/structures.py
insilicova/_sampler/__init__.py
insilicova/_sampler/sampler.cpp
insilicova/_sampler/_sampler.cpython-310-darwin.so
insilicova/data/randomva1.csv
insilicova/data/condprobnum.csv
insilicova/data/randomva2.csv
insilicova/data/condprob.csv
insilicova/data/randomva5.csv
insilicova/data/sample_physician.csv
insilicova/data/probbaseV3.csv
insilicova/data/probbase.csv
insilicova/data/sample_category.csv
insilicova/data/probbaseV5.csv
insilicova/data/random_physician.csv
insilicova/data/causetext.csv
insilicova/data/causetextV5.csv
