Metadata-Version: 2.1
Name: insilicova
Version: 0.1.3
Summary: Python implementation of the InSilicoVA Algorithm.
Author-email: Jason Thomas <jarathomas@gmail.com>, Sherry Zhao <zhao.3248@buckeyemail.osu.edu>
Maintainer-email: Jason Thomas <jarathomas@gmail.com>
License: GPLv3
Project-URL: Homepage, https://github.com/verbal-autopsy-software/pyinsilicova
Project-URL: Bug Tracker, https://github.com/verbal-autopsy-software/pyinsilicoVA/issues
Keywords: verbal autopsy
Classifier: Programming Language :: Python :: 3
Classifier: Programming Language :: Python :: 3.8
Classifier: Programming Language :: Python :: 3.9
Classifier: Programming Language :: Python :: 3.10
Classifier: Programming Language :: Python :: 3.11
Classifier: Programming Language :: Python :: 3.12
Classifier: License :: OSI Approved :: GNU General Public License v3 (GPLv3)
Classifier: Operating System :: OS Independent
Requires-Python: >=3.8
License-File: LICENSE
Requires-Dist: pandas
Requires-Dist: numpy
Requires-Dist: vacheck >=0.0.3
Requires-Dist: statsmodels
Requires-Dist: scipy
